dingtalkchatbot/__about__.py
dingtalkchatbot/__init__.py
dingtalkchatbot/chatbot.py
dingtalkchatbot/chatbot_test.py
dingtalkchatbot/samples.py
DingtalkChatbot-1.5.2.dist-info/METADATA
DingtalkChatbot-1.5.2.dist-info/WHEEL
DingtalkChatbot-1.5.2.dist-info/top_level.txt
DingtalkChatbot-1.5.2.dist-info/RECORD
