Metadata-Version: 1.2
Name: DingtalkChatbot
Version: 1.5.2
Summary: 一个钉钉自定义机器人消息的Python封装库
Home-page: https://github.com/zhuifengshen/DingtalkChatbot
Author: devin
Author-email: 1324556701@qq.com
License: MIT
Keywords: 钉钉 机器人 dingtalk chatbot robot bot
Platform: UNKNOWN
Classifier: Development Status :: 5 - Production/Stable
Classifier: Programming Language :: Python :: 2.7
Classifier: Programming Language :: Python :: 3.4
Classifier: Programming Language :: Python :: 3.5
Classifier: Programming Language :: Python :: 3.6
Classifier: Programming Language :: Python :: 3.7
Classifier: Programming Language :: Python :: 3.8
Classifier: Programming Language :: Python :: 3.9
Requires-Python: >=2.7, !=3.0.*, !=3.1.*, !=3.2.*, !=3.3.*, <4
